README.md
setup.cfg
setup.py
dshi/__init__.py
dshi/data_prep.py
dshi/eda.py
dshi/hi.py
dshi.egg-info/PKG-INFO
dshi.egg-info/SOURCES.txt
dshi.egg-info/dependency_links.txt
dshi.egg-info/top_level.txt